mycolab/__init__.py
mycolab/__main__.py
mycolab/common.py
mycolab/genbank.py
mycolab-1.0.8.dist-info/LICENSE
mycolab-1.0.8.dist-info/METADATA
mycolab-1.0.8.dist-info/WHEEL
mycolab-1.0.8.dist-info/dependency_links.txt
mycolab-1.0.8.dist-info/entry_points.txt
mycolab-1.0.8.dist-info/top_level.txt
mycolab-1.0.8.dist-info/RECORD
