Metadata-Version: 2.1
Name: mycolab
Version: 1.0.8
Summary: Command line tools for MycoLab
Home-page: https://github.com/mycolab/mycolab
Author: Joseph Harrison
Author-email: joe@mycolab.org
License: Apache Software
Download-URL: https://github.com/mycolab/mycolab/archive/1.0.7.tar.gz
Platform: UNKNOWN
Classifier: License :: OSI Approved :: Apache Software License
Classifier: Programming Language :: Python :: 3
Classifier: Programming Language :: Python :: 3.8
Requires-Python: >=3.0
Requires-Dist: requests
Requires-Dist: click
